st_img_pastebutton/__init__.py
st_img_pastebutton/frontend/build/asset-manifest.json
st_img_pastebutton/frontend/build/bootstrap.min.css
st_img_pastebutton/frontend/build/index.html
st_img_pastebutton/frontend/build/static/js/main.13c53392.js
st_img_pastebutton/frontend/build/static/js/main.13c53392.js.LICENSE.txt
st_img_pastebutton/frontend/build/static/js/main.13c53392.js.map
st_img_pastebutton/frontend/build/static/js/main.6a29b563.js
st_img_pastebutton/frontend/build/static/js/main.6a29b563.js.LICENSE.txt
st_img_pastebutton/frontend/build/static/js/main.6a29b563.js.map
st_img_pastebutton-0.0.6.dist-info/LICENSE
st_img_pastebutton-0.0.6.dist-info/METADATA
st_img_pastebutton-0.0.6.dist-info/WHEEL
st_img_pastebutton-0.0.6.dist-info/top_level.txt
st_img_pastebutton-0.0.6.dist-info/RECORD
