Metadata-Version: 2.1
Name: st-img-pastebutton
Version: 0.0.6
Summary: Streamlit component that allows you to create button to paste image from clipboard.
Home-page: UNKNOWN
Author: tsuzukia
Author-email: 
License: UNKNOWN
Platform: UNKNOWN
Requires-Python: >=3.7
Provides-Extra: devel
License-File: LICENSE
